lunespy/__init__.py
lunespy/client/transactions/__init__.py
lunespy/client/transactions/alias/__init__.py
lunespy/client/transactions/alias/validators.py
lunespy/client/transactions/burn/__init__.py
lunespy/client/transactions/burn/validators.py
lunespy/client/transactions/cancel_lease/__init__.py
lunespy/client/transactions/cancel_lease/validators.py
lunespy/client/transactions/constants.py
lunespy/client/transactions/lease/__init__.py
lunespy/client/transactions/lease/validators.py
lunespy/client/transactions/mass/__init__.py
lunespy/client/transactions/mass/validators.py
lunespy/client/transactions/reissue/__init__.py
lunespy/client/transactions/reissue/validators.py
lunespy/crypto/__init__.py
lunespy/server/address/__init__.py
lunespy/server/blocks/__init__.py
lunespy/server/nodes/__init__.py
lunespy/server/transactions/__init__.py
lunespy/tx/issue/__init__.py
lunespy/tx/issue/multi.py
lunespy/tx/issue/utils.py
lunespy/tx/sponsor/__init__.py
lunespy/tx/sponsor/utils.py
lunespy/tx/transfer/__init__.py
lunespy/tx/transfer/utils.py
lunespy/utils/__init__.py
lunespy/wallet/__init__.py
lunespy/wallet/assembly.py
lunespy/wallet/constants.py
lunespy-2.3.0.dist-info/LICENSE
lunespy-2.3.0.dist-info/WHEEL
lunespy-2.3.0.dist-info/METADATA
lunespy-2.3.0.dist-info/RECORD
